{"cameraMode":{"drawMode":0,"name":"Shaded","section":"Shading Mode"},"sceneLighting":false,"audioPlay":false,"sceneViewState":{"m_AlwaysRefresh":false,"showFog":true,"showSkybox":false,"showFlares":true,"showImageEffects":true,"showParticleSystems":true,"showVisualEffectGraphs":true,"m_FxEnabled":true},"in2DMode":false,"pivot":{"x":3.0,"y":2.0,"z":6.0},"rotation":{"x":0.22183822095394135,"y":-0.6243787407875061,"z":0.19134968519210816,"w":0.7241542935371399},"size":5.4772257804870609,"orthographic":false}